python_function_model/__init__.py
python_function_model/python_function_model.py
python_function_model-0.0.1.dist-info/METADATA
python_function_model-0.0.1.dist-info/WHEEL
python_function_model-0.0.1.dist-info/top_level.txt
python_function_model-0.0.1.dist-info/RECORD
