Metadata-Version: 2.1
Name: python-function-model
Version: 0.0.1
Summary: Model for Python function
Home-page: UNKNOWN
Author: Functions.Runtime
Author-email: UNKNOWN
License: UNKNOWN
Platform: UNKNOWN
